{
	"name": "BinaryDownload",
	"properties": {
		"linkedServiceName": {
			"referenceName": "AAG Data Lake",
			"type": "LinkedServiceReference"
		},
		"parameters": {
			"fileName": {
				"type": "string",
				"defaultValue": "nyiso.zip"
			},
			"folderName": {
				"type": "string",
				"defaultValue": "lnd"
			}
		},
		"annotations": [],
		"type": "Binary",
		"typeProperties": {
			"location": {
				"type": "AzureBlobFSLocation",
				"fileName": {
					"value": "@dataset().fileName",
					"type": "Expression"
				},
				"folderPath": {
					"value": "@dataset().folderName",
					"type": "Expression"
				},
				"fileSystem": "nyiso"
			}
		}
	}
}